LICENSE
README.md
setup.py
mphys/__init__.py
mphys/integrated_forces.py
mphys.egg-info/PKG-INFO
mphys.egg-info/SOURCES.txt
mphys.egg-info/dependency_links.txt
mphys.egg-info/not-zip-safe
mphys.egg-info/requires.txt
mphys.egg-info/top_level.txt
mphys/core/__init__.py
mphys/core/builder.py
mphys/core/coupling_group.py
mphys/core/distributed_converter.py
mphys/core/distributed_summer.py
mphys/core/mask_converter.py
mphys/core/mphys_group.py
mphys/core/multipoint.py
mphys/core/scenario.py
mphys/core/variable_convention.py
mphys/network/__init__.py
mphys/network/remote_component.py
mphys/network/server.py
mphys/network/server_manager.py
mphys/network/zmq_pbs.py
mphys/scenarios/__init__.py
mphys/scenarios/aerodynamic.py
mphys/scenarios/aeropropulsive.py
mphys/scenarios/aerostructural.py
mphys/scenarios/aerothermal.py
mphys/scenarios/geo_disp.py
mphys/scenarios/structural.py
mphys/utils/__init__.py
mphys/utils/directory_utils.py