Metadata-Version: 2.1
Name: mphys
Version: 2.0.0
Summary: Components and related code for multiphysics problems in OpenMDAO
Author: 
Author-email: 
License-File: LICENSE
Requires-Dist: numpy
Requires-Dist: openmdao!=3.27.0,>=3.25
Provides-Extra: remote
Requires-Dist: pbs4py; extra == "remote"
Requires-Dist: zmq; extra == "remote"
Provides-Extra: test
Requires-Dist: testflo; extra == "test"
Provides-Extra: docs
Requires-Dist: sphinx; extra == "docs"
Requires-Dist: sphinxcontrib.bibtex; extra == "docs"
Requires-Dist: pbs4py; extra == "docs"
Requires-Dist: zmq; extra == "docs"
Provides-Extra: all
Requires-Dist: pbs4py; extra == "all"
Requires-Dist: pbs4py; extra == "all"
Requires-Dist: sphinx; extra == "all"
Requires-Dist: sphinxcontrib.bibtex; extra == "all"
Requires-Dist: testflo; extra == "all"
Requires-Dist: zmq; extra == "all"
Requires-Dist: zmq; extra == "all"
